python-tusur/__init__.py
python-tusur/ajax.py
python-tusur/authorization.py
python-tusur/constants.py
python-tusur/exceptions.py
python-tusur/sdo.py
python-tusur/session.py
python_tusur/__init__.py
python_tusur/ajax.py
python_tusur/authorization.py
python_tusur/constants.py
python_tusur/exceptions.py
python_tusur/sdo.py
python_tusur/session.py
tests/__init__.py
tests/test_messages.py
tests/test_notifications.py
tests/test_ocenka.py
tests/test_timetable.py
python_tusur-0.4.1.dist-info/LICENSE
python_tusur-0.4.1.dist-info/METADATA
python_tusur-0.4.1.dist-info/WHEEL
python_tusur-0.4.1.dist-info/top_level.txt
python_tusur-0.4.1.dist-info/RECORD
