Metadata-Version: 2.1
Name: python-tusur
Version: 0.4.1
Summary: A project that allows you to work with tusur.ru via python
Home-page: https://github.com/Weebp-Team/python-tusur
Author: Tarodictrl
Author-email: vudi600@gmail.com
Keywords: python python3.7 tusur
Classifier: Programming Language :: Python :: 3.11
Classifier: License :: OSI Approved :: MIT License
Classifier: Operating System :: OS Independent
Requires-Python: >=3.7
License-File: LICENSE
Requires-Dist: requests >=2.31.0
Requires-Dist: beautifulsoup4 >=4.12.2
